mixver/cli/visualizer.py
mixver/config.py
mixver/storages/local_storage.py
mixver/versioning/exceptions.py
mixver/versioning/versioner.py
mixver-0.1.1.dist-info/LICENSE.txt
mixver-0.1.1.dist-info/WHEEL
mixver-0.1.1.dist-info/METADATA
mixver-0.1.1.dist-info/RECORD
