Metadata-Version: 2.1
Name: mixver
Version: 0.1.1
Summary: Custom versioning of ML models
Author: hectorLop
Author-email: lopez.almazan.hector@gmail.com
Requires-Python: >=3.9,<4.0
Classifier: Programming Language :: Python :: 3
Classifier: Programming Language :: Python :: 3.10
Classifier: Programming Language :: Python :: 3.9
Requires-Dist: rich (>=12.5.1,<13.0.0)
